pidng/__init__.py
pidng/bitunpack.c
pidng/core.py
pidng/dng.py
pidng/liblj92/Makefile
pidng/liblj92/lj92.c
pidng/liblj92/lj92.h
pidng-3.4.7.dist-info/WHEEL
pidng-3.4.7.dist-info/METADATA
pidng-3.4.7.dist-info/RECORD
