Metadata-Version: 2.1
Name: pidng
Version: 3.4.7
Summary: Python utility for converting Raspberry Pi Camera RAW images into Adobe DNG Format.
Home-page: https://github.com/schoolpost/PiDNG
Author: Csaba Nagy
Requires-Python: >=3.5,<4.0
Classifier: Programming Language :: Python :: 3
Classifier: Programming Language :: Python :: 3.5
Classifier: Programming Language :: Python :: 3.6
Classifier: Programming Language :: Python :: 3.7
Classifier: Programming Language :: Python :: 3.8
Classifier: Programming Language :: Python :: 3.9
Requires-Dist: exifread (>=2.3.2,<3.0.0)
Requires-Dist: numpy (>=1.14,<2.0)
Project-URL: Repository, https://github.com/schoolpost/PiDNG
